shewchuk/_shewchuk.py
shewchuk/__init__.py
shewchuk/_cshewchuk.cpython-313-aarch64-linux-gnu.so
shewchuk/py.typed
shewchuk-6.10.0.dist-info/top_level.txt
shewchuk-6.10.0.dist-info/RECORD
shewchuk-6.10.0.dist-info/LICENSE
shewchuk-6.10.0.dist-info/METADATA
shewchuk-6.10.0.dist-info/WHEEL
